<LevelMap>
  <Level name="abcd">
    <LayerData>
      <Layer name="Layer 50">(gs_a9{dynamic|image|E13_76},x=491.35,y=551.85,scaleX=0.7213798059647862,scaleY=0.46668389575707425,rotation=90.02168017980338,name=0.20471319369971752,density=1,restitution=0.1,friction=0,maskBit=2,groupBit=2,isBullet=undefined)(gs_a9{static|image|$a1973},x=430.9,y=527.9,scaleX=0.6630434782608696,scaleY=0.1820052452986918,rotation=90.02168017980338,name=0.6643853578716516,density=1,restitution=0.1,friction=0.5,maskBit=2,groupBit=2,isBullet=undefined)(gs_a9{dynamic|image|$a1974},x=147.35,y=594.3,scaleX=0.4304347826086957,scaleY=0.07486545485606609,rotation=-180,name=0.7412718432024121,density=1,restitution=0.1,friction=0,maskBit=2,groupBit=2,isBullet=undefined)(gs_a9{dynamic|image|$a1975},x=512.6,y=595.9,scaleX=0.5456521739130434,scaleY=0.07465558833730891,rotation=-180,name=0.862414238974452,density=1,restitution=0.1,friction=0,maskBit=2,groupBit=2,isBullet=undefined)(gs_a17{static|image|$a1976},x=561.95,y=595.6,scaleX=0.39325068870523416,scaleY=0.09113636363636363,rotation=0,name=0.14011290483176708,density=1,restitution=1,friction=0.5,maskBit=2,groupBit=2,isBullet=undefined)(gs_a15{dynamic|image|$a1977},x=543.25,y=578.3,scaleX=0.38172413793103455,scaleY=0.3985626710454296,rotation=0,name=0.0396414021961391,density=1,restitution=0.1,friction=0.5,maskBit=2,groupBit=2,isBullet=undefined)(gs_a9{static|image|$a1978},x=468.3,y=578.9,scaleX=0.6630434782608696,scaleY=0.28233911997494043,rotation=90.02168017980338,name=0.23256440460681915,density=1,restitution=0.1,friction=0.5,maskBit=2,groupBit=2,isBullet=undefined)(gs_a9{dynamic|image|$a1979},x=201.9,y=553.95,scaleX=0.4293478260869563,scaleY=0.2408915636232236,rotation=-180,name=0.7500846087932587,density=1,restitution=0.1,friction=0,maskBit=2,groupBit=2,isBullet=undefined)(gs_a9{dynamic|image|$a1980},x=483.25,y=554.25,scaleX=0.4304347826086956,scaleY=0.1540486851938584,rotation=-180,name=0.08057242026552558,density=1,restitution=0.1,friction=0,maskBit=2,groupBit=2,isBullet=undefined)(gs_a17{static|image|$a1981},x=81.9,y=634.3,scaleX=0.39325068870523416,scaleY=0.09113636363636363,rotation=0,name=0.14011290483176708,density=1,restitution=1,friction=0.5,maskBit=2,groupBit=2,isBullet=undefined)(gs_a17{dynamic|image|E13_77},x=88.6,y=545,scaleX=0.23327540672679745,scaleY=0.31157935599489517,rotation=0,name=0.6861262563616037,density=1,restitution=0.1,friction=0.5,maskBit=2,groupBit=2,isBullet=undefined)(gs_a15{dynamic|image|$a1982},x=52.6,y=601,scaleX=0.6003344481605353,scaleY=0.6189655172413793,rotation=0,name=0.5949299368076026,density=1,restitution=0.1,friction=0.5,maskBit=2,groupBit=2,isBullet=undefined)(gs_b9{dynamic|image|$a1983},x=488.05,y=370.65,scaleX=0.5122406789204843,scaleY=0.4073418423147278,rotation=90,name=0.6205858420580626,density=1,restitution=0.1,friction=0,maskBit=2,groupBit=2,isBullet=undefined)</Layer>
    </LayerData>
    <jointInfo>
      <joint>
        <anchorAx>16.880287459575996</anchorAx>
        <speed>0</speed>
        <anchorAy>99.8703536920139</anchorAy>
        <anchorBy>25.536606651404146</anchorBy>
        <bodyA>E13_76</bodyA>
        <bodyB>$a1974</bodyB>
        <type>revolute</type>
        <name>E13_76$a1974</name>
        <enabled>false</enabled>
        <anchorBx>-244.14260869565223</anchorBx>
        <torque>0</torque>
        <lowerAngle/>
        <upperAngle/>
      </joint>
      <joint>
        <anchorAx>-165.1599065756378</anchorAx>
        <speed>0</speed>
        <anchorAy>296.6709525327721</anchorAy>
        <anchorBy>293.40832901929844</anchorBy>
        <bodyA>E13_76</bodyA>
        <bodyB>$a1983</bodyB>
        <type>revolute</type>
        <name>E13_76$a1983</name>
        <enabled>false</enabled>
        <anchorBx>16.007521216265136</anchorBx>
        <torque>0</torque>
        <lowerAngle/>
        <upperAngle/>
      </joint>
      <joint>
        <anchorAx>21.17249730506648</anchorAx>
        <speed>0</speed>
        <anchorAy>97.39692904450139</anchorAy>
        <anchorBy>-18.740022553832873</anchorBy>
        <bodyA>E13_76</bodyA>
        <bodyB>$a1980</bodyB>
        <type>revolute</type>
        <name>E13_76$a1980</name>
        <enabled>false</enabled>
        <anchorBx>89.33673913043478</anchorBx>
        <torque>0</torque>
        <lowerAngle/>
        <upperAngle/>
      </joint>
      <joint>
        <anchorAx>18.142702120014373</anchorAx>
        <speed>0</speed>
        <anchorAy>99.8703536920139</anchorAy>
        <anchorBy>25.871894138294405</anchorBy>
        <bodyA>E13_76</bodyA>
        <bodyB>$a1975</bodyB>
        <type>revolute</type>
        <name>E13_76$a1975</name>
        <enabled>false</enabled>
        <anchorBx>121.13478260869564</anchorBx>
        <torque>0</torque>
        <lowerAngle/>
        <upperAngle/>
      </joint>
      <joint>
        <anchorAx>8.14131169476523</anchorAx>
        <speed>5</speed>
        <anchorAy>60.01018396461681</anchorAy>
        <anchorBy>3.9923275862068963</anchorBy>
        <bodyA>E13_77</bodyA>
        <bodyB>$a1982</bodyB>
        <type>revolute</type>
        <name>E13_77$609</name>
        <enabled>false</enabled>
        <anchorBx>44.15459866220737</anchorBx>
        <torque>1234</torque>
        <lowerAngle>0</lowerAngle>
        <upperAngle>90</upperAngle>
      </joint>
      <joint>
        <anchorAx>9.398691460055096</anchorAx>
        <speed>-5</speed>
        <anchorAy>12.139363636363633</anchorAy>
        <anchorBy>29.473709523809518</anchorBy>
        <bodyA>$a1976</bodyA>
        <bodyB>$a1977</bodyB>
        <type>revolute</type>
        <name>$a1976$348</name>
        <enabled>false</enabled>
        <anchorBx>28.07581034482759</anchorBx>
        <torque>345675435</torque>
        <lowerAngle/>
        <upperAngle/>
      </joint>
      <joint>
        <anchorAx>18.43125404240029</anchorAx>
        <speed>0</speed>
        <anchorAy>95.99687735723016</anchorAy>
        <anchorBy>-16.33244801365456</anchorBy>
        <bodyA>E13_76</bodyA>
        <bodyB>$a1979</bodyB>
        <type>revolute</type>
        <name>E13_76$a1979</name>
        <enabled>false</enabled>
        <anchorBx>-193.48559782608686</anchorBx>
        <torque>0</torque>
        <lowerAngle/>
        <upperAngle/>
      </joint>
      <joint>
        <anchorAx>14.805888429752066</anchorAx>
        <speed>5</speed>
        <anchorAy>10.667511363636363</anchorAy>
        <anchorBy>43.946551724137926</anchorBy>
        <bodyA>$a1981</bodyA>
        <bodyB>$a1982</bodyB>
        <type>revolute</type>
        <name>$a1981$348</name>
        <enabled>false</enabled>
        <anchorBx>44.09456521739132</anchorBx>
        <torque>345675435</torque>
        <lowerAngle/>
        <upperAngle/>
      </joint>
    </jointInfo>
  </Level>
</LevelMap>